pytensor_federated/__init__.py
pytensor_federated/common.py
pytensor_federated/op_async.py
pytensor_federated/py.typed
pytensor_federated/rpc.py
pytensor_federated/service.py
pytensor_federated/signatures.py
pytensor_federated/test_npproto.py
pytensor_federated/test_op_async.py
pytensor_federated/test_service.py
pytensor_federated/test_utils.py
pytensor_federated/test_wrapper_ops.py
pytensor_federated/utils.py
pytensor_federated/wrapper_ops.py
pytensor_federated/npproto/__init__.py
pytensor_federated/npproto/utils.py
pytensor_federated-1.0.2.dist-info/LICENSE
pytensor_federated-1.0.2.dist-info/METADATA
pytensor_federated-1.0.2.dist-info/WHEEL
pytensor_federated-1.0.2.dist-info/top_level.txt
pytensor_federated-1.0.2.dist-info/RECORD
