Metadata-Version: 2.1
Name: pytensor-federated
Version: 1.0.2
Summary: This package helps to reduce the amount of boilerplate code when creating Airflow DAGs from Python callables.
Home-page: https://github.com/michaelosthege/pytensor-federated
Download-URL: https://github.com/michaelosthege/pytensor-federated/tarball/1.0.2
Author: Michael Osthege
Author-email: michael.osthege@outlook.com
License: GNU Affero General Public License v3
Classifier: Programming Language :: Python
Classifier: Operating System :: OS Independent
Classifier: Programming Language :: Python :: 3.10
Classifier: Programming Language :: Python :: 3.11
Classifier: License :: OSI Approved :: GNU Affero General Public License v3
License-File: LICENSE
Requires-Dist: betterproto==2.0.0b7
Requires-Dist: black
Requires-Dist: isort
Requires-Dist: nest-asyncio
Requires-Dist: numpy
Requires-Dist: psutil
